[{           "fname": "Deepali",
            "lname": "Kakade",
            "id": 1,
            "email": "dkakade1@gmail.com",
            "username" :"deepalik",
            "password": "deepali123",
            "courses": [
                {
					"id": 1,
                    "name": "Fundamentals of AngularJs",
                    "creatorName": "Bob Smith",
                    "creatorPhoto":"/assets/img/auth1.jpg",
                    "duration": 1,
                    "level": "Advanced",
                    "abstract": "In this session you will learn the fundamental concepts of angularjs!Learn what they do, how they do it",
                    "upvoteCount": 110,
                    "price":"$150",
                    "courseImg" :"/assets/img/angularjs.jpg"
                },
                {
					"id": 2,
                    "name": "GIT Fundamentals",
                    "creatorName": "John Doe",
                    "creatorPhoto":"/assets/img/auth2.jpg",
                    "duration": 3,
                    "level": "Introductory",
                    "abstract": "This session will take a closer look at scopes.  Learn what they do, how they do it, and how to get them to do it for you.",
                    "upvoteCount": 30,
                    "price":"$200",
                    "courseImg" :"/assets/img/github.jpg"
                },
                {
					"id": 3,
                    "name": "Introduction to MangoDB",
                    "creatorName": "Jane Smith",
                    "creatorPhoto":"/assets/img/auth3.jpg",
                    "duration": 2,
                    "level": "Intermediate",
                    "abstract": "Controllers are the beginning of everything Angular does.  Learn how to craft controllers that will win the respect of your friends and neighbors.",
                    "upvoteCount": 90,
                    "price":"$250",
                    "courseImg" :"/assets/img/mangodb.png"
                },
                {
                    "id": 4,
                    "name": "Bootstrap",
                    "creatorName": "John Doe",
                    "creatorPhoto":"/assets/img/auth2.jpg",
                    "duration": 3,
                    "level": "Introductory",
                    "abstract": "This session will take a closer look at responsive framework.Learn how it works and what it do.and how to get them to do it for you",
                    "upvoteCount": 30,
                    "price":"$200",
                    "courseImg" :"/assets/img/bootstrap.jpg"
                },
                {
                    "id": 5,
                    "name": "Introduction ASP.Net",
                    "creatorName": "Jane Smith",
                    "creatorPhoto":"/assets/img/auth3.jpg",
                    "duration": 2,
                    "level": "Intermediate",
                    "abstract": "Controllers are the beginning of everything Angular does.  Learn how to craft controllers that will win the respect of your friends and neighbors.",
                    "upvoteCount": 90,
                    "price":"$250",
                    "courseImg" :"/assets/img/asp.jpg"
                },
                {
                    "id": 6,
                    "name": "Introduction HTML5",
                    "creatorName": "Jane Smith",
                    "creatorPhoto":"/assets/img/auth3.jpg",
                    "duration": 2,
                    "level": "Intermediate",
                    "abstract": "Controllers are the beginning of everything Angular does.  Learn how to craft controllers that will win the respect of your friends and neighbors.",
                    "upvoteCount": 90,
                    "price":"$250",
                    "courseImg" :"/assets/img/html5.jpg"
                },
                {
                    "id": 7,
                    "name": "jQuery",
                    "creatorName": "John Doe",
                    "creatorPhoto":"/assets/img/auth2.jpg",
                    "duration": 3,
                    "level": "Introductory",
                    "abstract": "This session will take a closer look at responsive framework.Learn how it works and what it do.and how to get them to do it for you",
                    "upvoteCount": 30,
                    "price":"$200",
                    "courseImg" :"/assets/img/jquery.png"
                },
                {
                    "id": 8,
                    "name": "Introduction to MVC",
                    "creatorName": "Jane Smith",
                    "creatorPhoto":"/assets/img/auth3.jpg",
                    "duration": 2,
                    "level": "Intermediate",
                    "abstract": "Controllers are the beginning of everything Angular does.  Learn how to craft controllers that will win the respect of your friends and neighbors.",
                    "upvoteCount": 90,
                    "price":"$250",
                    "courseImg" :"/assets/img/mvc.jpg"
                },
                {
                    "id": 9,
                    "name": "PHP",
                    "creatorName": "Jane Smith",
                    "creatorPhoto":"/assets/img/auth3.jpg",
                    "duration": 2,
                    "level": "Intermediate",
                    "abstract": "Controllers are the beginning of everything Angular does.  Learn how to craft controllers that will win the respect of your friends and neighbors.",
                    "upvoteCount": 90,
                    "price":"$250",
                    "courseImg" :"/assets/img/php.jpg"
                }
            ]
},
{           "fname": "Geet",
            "lname": "Khabale",
            "id": 2,
            "email": "geetk@gmail.com",
            "username" :"geetk",
            "password": "geet123",
            "courses": [
                
                {
                    "id": 1,
                    "name": "GIT Fundamentals",
                    "creatorName": "John Doe",
                    "creatorPhoto":"/assets/img/auth2.jpg",
                    "duration": 3,
                    "level": "Introductory",
                    "abstract": "This session will take a closer look at scopes.  Learn what they do, how they do it, and how to get them to do it for you.",
                    "upvoteCount": 30,
                    "price":"$200",
                    "courseImg" :"/assets/img/github.jpg"
                },
                {
                    "id": 2,
                    "name": "Fundamentals of AngularJs",
                    "creatorName": "Bob Smith",
                    "creatorPhoto":"/assets/img/auth1.jpg",
                    "duration": 1,
                    "level": "Advanced",
                    "abstract": "In this session you will learn the fundamental concepts of angularjs!Learn what they do, how they do it",
                    "upvoteCount": 110,
                    "price":"$150",
                    "courseImg" :"/assets/img/angularjs.jpg"
                },
                {
                    "id": 3,
                    "name": "Introduction to MangoDB",
                    "creatorName": "Jane Smith",
                    "creatorPhoto":"/assets/img/auth3.jpg",
                    "duration": 2,
                    "level": "Intermediate",
                    "abstract": "Controllers are the beginning of everything Angular does.  Learn how to craft controllers that will win the respect of your friends and neighbors.",
                    "upvoteCount": 90,
                    "price":"$250",
                    "courseImg" :"/assets/img/mangodb.png"
                }
            ]
        }
 ]